py14_9199/__init__.py
py14_9199/greetings.py
py14_9199/math_ops.py
py14_9199-0.1.0.dist-info/METADATA
py14_9199-0.1.0.dist-info/WHEEL
py14_9199-0.1.0.dist-info/top_level.txt
py14_9199-0.1.0.dist-info/RECORD
