Metadata-Version: 2.4
Name: py14_9199
Version: 0.1.0
Summary: A custom package with greetings and math operations
Author: notes
Author-email: mscsoftwaresystemsnotes@email.com
License: MIT
Dynamic: author
Dynamic: author-email
Dynamic: license
Dynamic: summary
